mppbar/__init__.py
mppbar/mppbar.py
mppbar-0.1.5.dist-info/METADATA
mppbar-0.1.5.dist-info/WHEEL
mppbar-0.1.5.dist-info/namespace_packages.txt
mppbar-0.1.5.dist-info/top_level.txt
mppbar-0.1.5.dist-info/zip-safe
mppbar-0.1.5.dist-info/RECORD
