Metadata-Version: 2.1
Name: mppbar
Version: 0.1.5
Summary: A multi-processing enabled progress bar.
Home-page: https://github.com/soda480/mppbar
Author: Emilio Reyes
Author-email: soda480@gmail.com
Maintainer: 
Maintainer-email: 
License: Apache License, Version 2.0
Classifier: Programming Language :: Python
Classifier: Programming Language :: Python :: 3.7
Classifier: Programming Language :: Python :: 3.8
Classifier: Programming Language :: Python :: 3.9
Classifier: Programming Language :: Python :: 3.10
Requires-Dist: mpmq (~=0.3.2)
Requires-Dist: cursor (~=1.3.5)
Requires-Dist: colorama (~=0.4.5)
Requires-Dist: progress1bar (~=0.2.6)
Requires-Dist: list2term (~=0.1.0)
